sungear/__init__.py
sungear/__main__.py
sungear/cli.py
sungear/server.py
sungear/utils.py
sungear/static/Nemhauser_et_al_hormones.txt
sungear/static/index.html
sungear/static/main.0ef5421282d3d88ed55d.js
sungear/static/main.11636bad9b9977f9c216.js
sungear/static/main.2298dc8925e93a3a8d3a.js
sungear/static/main.27325c3fd67cf6ee6934.js
sungear/static/main.277f55b393477c237208.js
sungear/static/main.414be71ed6ee7f9516c0.js
sungear/static/main.6bfa9a989ef26b87859f.js
sungear/static/main.7be25bb8bfa38149522d.js
sungear/static/main.a3d426303f6710dc3f83.js
sungear/static/main.bbf230bff13502dc0fe0.js
sungear/static/main.c9d0507dc21712c9ac3f.js
sungear/static/main.d5c8373226bad9fe164b.js
sungear/static/main.d828bff47a0bd4a6fa84.js
sungear/static/main.da27b7ab139dfb6bf5b5.js
sungear/static/main.e63419dfd343dab50d6c.js
sungear/static/main.e645f0ace30a0588235c.js
sungear/static/main.ee4415864dc1fbb6d0a2.js
sungear/static/runtime.b24c5ac6668d34a8962b.js
sungear/static/runtime.d02150126965da0aef6f.js
sungear/static/vendors.29a61fbf3f8e52c590a1.css
sungear/static/vendors.39c82bd5501fd38ddcb5.js
sungear/static/vendors.3e374aa1da15fdc3bcaa.css
sungear/static/vendors.784105c462348f20e0f1.js
sungear/static/vendors.80e6ffb2156d27a80a3b.js
sungear/static/vendors.92ba994145adaaa18c06.js
sungear/static/vendors.945367f9df98979ecc80.js
sungear/static/vendors.b9afcb10fa801e48ec41.js
sungear/static/vendors.dba44ddcebfff9bb1424.js
sungear/static/vendors.f7a0b2b33ac04bc02e36.js
sungear-1.1.3.dist-info/LICENSE
sungear-1.1.3.dist-info/METADATA
sungear-1.1.3.dist-info/WHEEL
sungear-1.1.3.dist-info/top_level.txt
sungear-1.1.3.dist-info/RECORD
