Metadata-Version: 2.1
Name: sungear
Version: 1.1.3
Summary: Web based Sungear visualization.
Home-page: https://github.com/zachary822/sungear
Author: Zachary Juang
Author-email: zacharyjuang+sungear@gmail.com
License: UNKNOWN
Project-URL: Bug Reports, https://github.com/zachary822/sungear/issues
Platform: UNKNOWN
Classifier: Development Status :: 3 - Alpha
Classifier: License :: OSI Approved :: MIT License
Classifier: Programming Language :: Python :: 3.6
Classifier: Programming Language :: Python :: 3.7
Requires-Python: >=3.6
Requires-Dist: numpy
Requires-Dist: pandas
Requires-Dist: scikit-learn
Requires-Dist: scipy
Requires-Dist: statsmodels
Provides-Extra: web
Requires-Dist: flask ; extra == 'web'
